.gitignore
.gitmodules
.travis.yml
AUTHORS
LICENSE
MANIFEST.in
README.rst
requirements.txt
setup.cfg
setup.py
FoLiA.egg-info/PKG-INFO
FoLiA.egg-info/SOURCES.txt
FoLiA.egg-info/dependency_links.txt
FoLiA.egg-info/not-zip-safe
FoLiA.egg-info/requires.txt
FoLiA.egg-info/top_level.txt
docs/Makefile
docs/source/conf.py
docs/source/folia.rst
docs/source/index.rst
docs/source/_templates/foliaelement.rst
docs/source/_templates/fullclass.rst
folia/__init__.py
folia/foliaset.py
folia/fql.py
folia/helpers.py
folia/main.py
folia/tests/__init__.py
folia/tests/folia_benchmark.py
folia/tests/fql.py
folia/tests/helpers.py
folia/tests/maintest.py
folia/tests/test.sh
folia/tests/testallexamples.py