Metadata-Version: 2.1
Name: FoLiA
Version: 2.5.9
Summary: An extensive library for processing FoLiA documents. FoLiA stands for Format for Linguistic Annotation and is a very rich XML-based format used by various Natural Language Processing tools.
Home-page: https://github.com/proycon/foliapy
Author: Maarten van Gompel
Author-email: proycon@anaproy.nl
License: GPL-3.0-only
Keywords: nlp,computational linguistics,folia,format,xml,annotation
Classifier: Development Status :: 5 - Production/Stable
Classifier: Topic :: Text Processing :: Linguistic
Classifier: Programming Language :: Python :: 3
Classifier: Operating System :: POSIX
Classifier: Intended Audience :: Developers
Classifier: Intended Audience :: Science/Research
Classifier: License :: OSI Approved :: GNU General Public License v3 (GPLv3)
Requires-Python: >=3.7
License-File: LICENSE
License-File: AUTHORS
